openflexure_microscope/__init__.py
openflexure_microscope/__main__.py
openflexure_microscope/basic_serial_instrument.py
openflexure_microscope/keyboard_control.py
openflexure_microscope/microscope.py
openflexure_microscope/microscope_control.py
openflexure_microscope/openflexure_stage.py
openflexure_microscope/utilities/__init__.py
openflexure_microscope/utilities/recalibrate_microscope.py
openflexure_microscope/utilities/recalibrate_microscope_closedloop.py
openflexure_microscope-0.1.1.dist-info/DESCRIPTION.rst
openflexure_microscope-0.1.1.dist-info/METADATA
openflexure_microscope-0.1.1.dist-info/RECORD
openflexure_microscope-0.1.1.dist-info/WHEEL
openflexure_microscope-0.1.1.dist-info/metadata.json
openflexure_microscope-0.1.1.dist-info/top_level.txt
openflexure_microscope-0.1.1.dist-info/zip-safe
