Metadata-Version: 2.0
Name: openflexure-microscope
Version: 0.1.1
Summary: Control scripts for the OpenFlexure Microscope
Home-page: http://www.github.com/rwb27/openflexure_microscope_software
Author: Richard Bowman
Author-email: r.w.bowman@bath.ac.uk
License: UNKNOWN
Download-URL: https://github.com/rwb27/openflexure_microscope_software/archive/0.1.1.tar.gz
Keywords: arduino,serial,microscope
Platform: UNKNOWN
Classifier: Development Status :: 4 - Beta
Classifier: License :: OSI Approved :: GNU General Public License v3 (GPLv3)
Classifier: Programming Language :: Python :: 2.7
Requires-Dist: matplotlib
Requires-Dist: numpy
Requires-Dist: opencv
Requires-Dist: openflexure-stage
Requires-Dist: picamera
Requires-Dist: pyserial
Requires-Dist: scipy
